{
    "AX": {
        "error": 0.004085183872278519, 
        "filter_outliers_dict": {
            "filter_outliers": true, 
            "iterations": 1, 
            "std_devs": 2
        }, 
        "fit": "average", 
        "value": 0.05534978287182538
    }, 
    "CDD": {
        "error": 3.624747194411086e-06, 
        "filter_outliers_dict": {
            "filter_outliers": true, 
            "iterations": 1, 
            "std_devs": 10
        }, 
        "fit": "average", 
        "value": 1.1259289046431724e-05
    }, 
    "H1": {
        "error": 0.003484046281284588, 
        "filter_outliers_dict": {
            "filter_outliers": true, 
            "iterations": 1, 
            "std_devs": 2
        }, 
        "fit": "average", 
        "value": -0.032599515831882996
    }, 
    "H2": {
        "error": 0.003830481555577448, 
        "filter_outliers_dict": {
            "filter_outliers": true, 
            "iterations": 1, 
            "std_devs": 2
        }, 
        "fit": "average", 
        "value": 0.05719570142654195
    }, 
    "L1": {
        "error": 0.0015669045387607585, 
        "filter_outliers_dict": {
            "filter_outliers": true, 
            "iterations": 1, 
            "std_devs": 2
        }, 
        "fit": "average", 
        "value": -0.008788001876578671
    }, 
    "L2": {
        "error": 0.0036833142219487598, 
        "filter_outliers_dict": {
            "filter_outliers": true, 
            "iterations": 1, 
            "std_devs": 2
        }, 
        "fit": "average", 
        "value": 0.15642118981937495
    }
}